{
    "room":   "Medúzky CZ/SK",
    "author": "Máro",
    "css":    "https://cdn.rawgit.com/Maro1310/Meduzky/555627d1/style.css",
    "rules": {
        "allowAutorespond": true,
        "allowAutowoot":    true,
        "allowAutojoin":    true,
        "allowAutograb":    true,
        "allowSmartVote":   true,
        "allowEmotes":      true,
        "allowShowingMehs": true,
        "forceSmartVote":   false
    },
    "images": {
        "playback": "https://i.imgur.com/eKoIQDS.png"
    },
    "emotes": {
    }
}

